MANIFEST.in
README.rst
setup.py
trovebox/__init__.py
trovebox/_version.py
trovebox/auth.py
trovebox/errors.py
trovebox/http.py
trovebox/main.py
trovebox.egg-info/PKG-INFO
trovebox.egg-info/SOURCES.txt
trovebox.egg-info/dependency_links.txt
trovebox.egg-info/entry_points.txt
trovebox.egg-info/requires.txt
trovebox.egg-info/top_level.txt
trovebox.egg-info/zip-safe
trovebox/api/__init__.py
trovebox/api/api_action.py
trovebox/api/api_activity.py
trovebox/api/api_album.py
trovebox/api/api_base.py
trovebox/api/api_photo.py
trovebox/api/api_system.py
trovebox/api/api_tag.py
trovebox/objects/__init__.py
trovebox/objects/action.py
trovebox/objects/activity.py
trovebox/objects/album.py
trovebox/objects/photo.py
trovebox/objects/tag.py
trovebox/objects/trovebox_object.py