Metadata-Version: 1.1
Name: trovebox
Version: 0.6
Summary: The official Python client library for the Trovebox photo service
Home-page: https://github.com/photo/openphoto-python
Author: Pete Burgers, James Walker
Author-email: UNKNOWN
License: Apache 2.0
Keywords: openphoto,pyopenphoto,openphoto-python,trovebox,pytrovebox,trovebox-python
Platform: UNKNOWN
Classifier: Development Status :: 4 - Beta
Classifier: Intended Audience :: Developers
Classifier: License :: OSI Approved :: Apache Software License
Classifier: Operating System :: OS Independent
Classifier: Programming Language :: Python
Classifier: Topic :: Multimedia :: Graphics
Classifier: Topic :: Software Development :: Libraries :: Python Modules
